pyvis_timeline/.DS_Store
pyvis_timeline/__about__.py
pyvis_timeline/__init__.py
pyvis_timeline/__pycache__/__about__.cpython-38.pyc
pyvis_timeline/__pycache__/__init__.cpython-38.pyc
pyvis_timeline/examples/__init__.py
pyvis_timeline/examples/_dataset.py
pyvis_timeline/examples/__pycache__/__init__.cpython-38.pyc
pyvis_timeline/examples/__pycache__/_dataset.cpython-38.pyc
pyvis_timeline/examples/data/COVID19_Variants_Date_of_Designation.csv
pyvis_timeline/examples/data/README.txt
pyvis_timeline/examples/data/__init__.py
pyvis_timeline/examples/data/__pycache__/__init__.cpython-38.pyc
pyvis_timeline/examples/images/covid19_variants_designation_timeline.png
pyvis_timeline/timeline/__init__.py
pyvis_timeline/timeline/_timeline.py
pyvis_timeline/timeline/__pycache__/__init__.cpython-38.pyc
pyvis_timeline/timeline/__pycache__/_timeline.cpython-38.pyc
pyvis_timeline-0.0.8.dist-info/LICENSE
pyvis_timeline-0.0.8.dist-info/METADATA
pyvis_timeline-0.0.8.dist-info/WHEEL
pyvis_timeline-0.0.8.dist-info/top_level.txt
pyvis_timeline-0.0.8.dist-info/RECORD
